navx/__init__.py
navx/py.typed
navx/version.py
navx/src/rpy/navx.cpp
navx/_init__navx.py
navx/_navx.cp311-win_amd64.lib
navx/_navx.cp311-win_amd64.pyd
navx/_navx.pyi
navx/navx.pc
navx/trampolines/__studica__AHRS.hpp
navx/trampolines/__studica__AHRS__BoardYawAxis.hpp
navx/trampolines/__studica__Navx.hpp
robotpy_navx-2026.0.0.dist-info/METADATA
robotpy_navx-2026.0.0.dist-info/WHEEL
robotpy_navx-2026.0.0.dist-info/entry_points.txt
robotpy_navx-2026.0.0.dist-info/RECORD
