Metadata-Version: 2.4
Name: robotpy-navx
Version: 2026.0.0
Summary: Python wrapper for Studica NavX sensor
Project-URL: Source code, https://github.com/robotpy/robotpy-navx
Author-email: RobotPy Development Team <robotpy@googlegroups.com>
License-Expression: BSD-3-Clause
Requires-Dist: wpilib<2027,>=2026.1.1
